traveltime_google_comparison/__init__.py
traveltime_google_comparison/analysis.py
traveltime_google_comparison/collect.py
traveltime_google_comparison/config.py
traveltime_google_comparison/main.py
traveltime_google_comparison/requests/__init__.py
traveltime_google_comparison/requests/base_handler.py
traveltime_google_comparison/requests/factory.py
traveltime_google_comparison/requests/google_handler.py
traveltime_google_comparison/requests/here_handler.py
traveltime_google_comparison/requests/mapbox_handler.py
traveltime_google_comparison/requests/openroutes_handler.py
traveltime_google_comparison/requests/osrm_handler.py
traveltime_google_comparison/requests/tomtom_handler.py
traveltime_google_comparison/requests/traveltime_credentials.py
traveltime_google_comparison/requests/traveltime_handler.py
traveltime_google_comparison-1.1.1.dist-info/LICENSE
traveltime_google_comparison-1.1.1.dist-info/METADATA
traveltime_google_comparison-1.1.1.dist-info/WHEEL
traveltime_google_comparison-1.1.1.dist-info/entry_points.txt
traveltime_google_comparison-1.1.1.dist-info/top_level.txt
traveltime_google_comparison-1.1.1.dist-info/RECORD
