Metadata-Version: 2.1
Name: traveltime-google-comparison
Version: 1.1.1
Summary: Compare travel times obtained from TravelTime API and Google Maps API
Author: TravelTime
Project-URL: Homepage, https://github.com/traveltime-dev/traveltime-google-comparison
Classifier: Programming Language :: Python :: 3
Classifier: Programming Language :: Python :: 3.8
Classifier: Programming Language :: Python :: 3.9
Classifier: Programming Language :: Python :: 3.10
Classifier: Programming Language :: Python :: 3.11
Classifier: Programming Language :: Python :: 3.12
Classifier: License :: OSI Approved :: MIT License
Requires-Python: >=3.8
License-File: LICENSE
Requires-Dist: aiohttp
Requires-Dist: aiolimiter
Requires-Dist: pandas
Requires-Dist: pytz
Requires-Dist: traveltimepy
Provides-Extra: test
Requires-Dist: pytest; extra == "test"
Requires-Dist: flake8; extra == "test"
Requires-Dist: flake8-pyproject; extra == "test"
Requires-Dist: mypy; extra == "test"
Requires-Dist: black; extra == "test"
